Users/Administrator/.config/gplaycli/cronjob
Users/Administrator/.config/gplaycli/gplaycli.conf
gplaycli/__init__.py
gplaycli/__main__.py
gplaycli/gplaycli.py
gplaycli/hooks.py
gplaycli/util.py
vGPlayCli-3.24.12.dist-info/METADATA
vGPlayCli-3.24.12.dist-info/RECORD
vGPlayCli-3.24.12.dist-info/WHEEL
vGPlayCli-3.24.12.dist-info/entry_points.txt
vGPlayCli-3.24.12.dist-info/top_level.txt
