Metadata-Version: 2.1
Name: vGPlayCli
Version: 3.24.12
Summary: GPlayCli, a Google play downloader command line interface
Home-page: https://github.com/matlink/gplaycli
Author: Matlink
Author-email: matlink@matlink.fr
License: AGPLv3
Platform: UNKNOWN
Requires-Dist: vgpapi (==0.4.3.5)
Requires-Dist: pyaxmlparser
Requires-Dist: pysocks
